packageneha/__init__.py
packageneha-0.0.1.dist-info/METADATA
packageneha-0.0.1.dist-info/WHEEL
packageneha-0.0.1.dist-info/top_level.txt
packageneha-0.0.1.dist-info/RECORD
