Metadata-Version: 2.1
Name: packageneha
Version: 0.0.1
Summary: dit document layout
Author: snehadhole
License: UNKNOWN
Platform: UNKNOWN
Requires-Dist: torch
Requires-Dist: pyyaml
Requires-Dist: torchvision
Requires-Dist: opencv-python
